jsonupdate_ng/__init__.py
jsonupdate_ng/jsonupdate_ng.py
jsonupdate_ng/version.py
jsonupdate_ng-1.0.3.dist-info/LICENSE
jsonupdate_ng-1.0.3.dist-info/METADATA
jsonupdate_ng-1.0.3.dist-info/WHEEL
jsonupdate_ng-1.0.3.dist-info/top_level.txt
jsonupdate_ng-1.0.3.dist-info/RECORD
