Metadata-Version: 2.1
Name: jsonupdate-ng
Version: 1.0.3
Summary: A Next Generation Library to update any json document
Home-page: https://gitlab.sas.com/sindec/rf-rest
Author: Deepak Chourasia
Author-email: deepak.chourasia@gmail.com
Project-URL: Bug Tracker, https://gitlab.sas.com/sindec/jsonupdate-ng
Classifier: Programming Language :: Python :: 3
Classifier: License :: OSI Approved :: Apache Software License
Classifier: Intended Audience :: Developers
Classifier: Natural Language :: English
Classifier: Topic :: Software Development :: Testing
Classifier: Development Status :: 5 - Production/Stable
Requires-Python: >=3.5.2
License-File: LICENSE
